pyetcd/__init__.py
pyetcd/client.py
pyetcd-1.11.1.dist-info/METADATA
pyetcd-1.11.1.dist-info/RECORD
pyetcd-1.11.1.dist-info/WHEEL
pyetcd-1.11.1.dist-info/top_level.txt
