Metadata-Version: 2.1
Name: pyetcd
Version: 1.11.1
Summary: Python library to work with Etcd
Home-page: https://github.com/twindb/pyetcd
Author: TwinDB Development Team
Author-email: dev@twindb.com
License: Apache Software License 2.0
Keywords: pyetcd
Platform: UNKNOWN
Classifier: Development Status :: 2 - Pre-Alpha
Classifier: Intended Audience :: Developers
Classifier: License :: OSI Approved :: Apache Software License
Classifier: Natural Language :: English
Classifier: Programming Language :: Python :: 2
Classifier: Programming Language :: Python :: 2.7
Classifier: Programming Language :: Python :: 3
Classifier: Programming Language :: Python :: 3.4
Classifier: Programming Language :: Python :: 3.5
Classifier: Programming Language :: Python :: 3.6
Requires-Dist: requests
